rtl_cache/l1cache.v
module l1cache(
    input logic reset,
    input logic clk,

    //CPU side connections
    input logic read_cpu,
    input logic write_cpu,
    input logic[31:0] addr_cpu,
    input logic[3:0] byteenable_cpu,
    input logic [31:0] writedata_cpu,
    output logic [31:0] readdata_cpu,
    output logic waitrequest_cpu,

    //Ram side connections
    output logic read_ram,
    output logic write_ram,
    output logic[31:0] addr_ram,
    output logic[3:0] byteenable_ram,
    output logic [31:0] writedata_ram,
    input logic [31:0] readdata_ram,
    input logic waitrequest_ram
);

//This memory is Avalon compliant and implements 1024 memory locations after
logic[31:0] mem0[1024-1:0];
logic[31:0] mem1[1024-1:0];
logic[31:0] mem2[1024-1:0];
logic[31:0] mem3[1024-1:0];

//Queue variables
logic[31:0] address_queue[3:0];
logic[3:0] valid_queue;
logic last_queue_valid;
logic[31:0] last_queue_address;
logic[19:0] last_tag_ram;
logic last_ram_waitrequest;

logic[9:0] block_id_cpu, last_block_id_ram;
logic[19:0] tag[1024-1:0];
logic valid[1024-1:0];
logic[31:0] readdata_internal;

logic[31:0] ram_write_word;
logic[7:0] hi, lo, midhi, midlo;
logic[19:0] tag_cpu;
logic hit, last_hit, last_cpu_write, last_cpu_read, last_ram_write, last_ram_read;

//Viewers of address queue
logic[31:0] viewer_address_queue0;
assign viewer_address_queue0 = address_queue[0];
logic[31:0] viewer_address_queue1;
assign viewer_address_queue1 = address_queue[1];
logic[31:0] viewer_address_queue2;
assign viewer_address_queue2 = address_queue[2];
logic[31:0] viewer_address_queue3;
assign viewer_address_queue3 = address_queue[3];

logic viewer_valid;
assign viewer_valid = valid[4];
logic[19:0] viewer_tag;
assign viewer_tag = tag[4];
logic[31:0] viewer_mem0;
assign viewer_mem0 = mem0[4];
logic[31:0] viewer_mem1;
assign viewer_mem1 = mem1[4];
logic[31:0] viewer_mem2;
assign viewer_mem2 = mem2[4];
logic[31:0] viewer_mem3;
assign viewer_mem3 = mem3[4];


//Reset initialization
always @(posedge clk) begin
    readdata_cpu <= {hi, midhi, midlo, lo};
    last_queue_address <= address_queue[0];
    last_ram_waitrequest <= waitrequest_ram;
    last_queue_valid <= valid_queue[0];
    last_ram_write <= write_ram;
    last_ram_read <= read_ram;

    if(reset) begin
        valid_queue<= 0;
        last_queue_valid <= 0;
        for( int i =0; i < 1024 ; i++) begin
            valid[i] <= 0;
            tag[i] <= 0;
        end
    end
    else begin
        //Write bodge
        if(hit & write_cpu) begin
            valid[block_id_cpu] <=0;
        end

       //Writeback
        if (~last_ram_waitrequest & last_queue_valid & ~last_ram_write & last_ram_read) begin
            if(last_queue_address[1:0] == 0) begin
                mem0[last_block_id_ram]<=readdata_ram;
            end
            else if(last_queue_address[1:0] == 1) begin
                mem1[last_block_id_ram]<=readdata_ram;
            end
            else if(last_queue_address[1:0] == 2) begin
                mem2[last_block_id_ram]<=readdata_ram;
            end
            else if(last_queue_address[1:0] == 3) begin
                mem3[last_block_id_ram]<=readdata_ram;
            end
        end


        //Queue fill
        if(read_cpu & ~hit & valid_queue == 0 & ~last_queue_valid) begin
            valid_queue <= 15;
            address_queue[3] <= {addr_cpu[31:2], 2'b00};
            address_queue[2] <= {addr_cpu[31:2], 2'b01};
            address_queue[1] <= {addr_cpu[31:2], 2'b10};
            address_queue[0] <= {addr_cpu[31:2], 2'b11};
        end
        //Queue shift
        else if(~waitrequest_ram & ~write_cpu) begin

            //Valid queue
            valid_queue[3] <= 0;
            valid_queue[2] <= valid_queue[3];
            valid_queue[1] <= valid_queue[2];
            valid_queue[0] <= valid_queue[1];

            //Address queue
            address_queue[3] <= 0;
            address_queue[2] <= address_queue[3];
            address_queue[1] <= address_queue[2];
            address_queue[0] <= address_queue[1];

        end
        //Block loading finished
        if(valid_queue == 0 && last_queue_valid) begin
            valid[last_block_id_ram] <= 1;
        end
    end
end

//Cpu waitreq control and word resolution

always @(*) begin
    //Misc decoding
    tag_cpu = addr_cpu[31: 12];
    block_id_cpu = addr_cpu[11 :2];
    hit = valid[block_id_cpu] && (tag[block_id_cpu] == tag_cpu);
    last_tag_ram = last_queue_address[2 : 2];
    last_block_id_ram = last_queue_address[11 :2];


    if(write_cpu) begin
            write_ram = 1;
            read_ram = 0;
            addr_ram = addr_cpu;
            writedata_ram = writedata_cpu;
    end
    else if(read_cpu)begin
        write_ram = 0;
        addr_ram = address_queue[0];
        if(hit) begin
            waitrequest_cpu = 0;
            read_ram = 0;
            if(addr_cpu[1:0] == 0) begin
               readdata_internal = mem0[block_id_cpu];
            end
            else if(addr_cpu[1:0] == 1) begin
               readdata_internal = mem1[block_id_cpu];
            end
            else if(addr_cpu[1:0] == 2) begin
               readdata_internal = mem2[block_id_cpu];
            end
            else begin
               readdata_internal = mem3[block_id_cpu];
            end
        end
        else if(valid_queue != 0) begin
            waitrequest_cpu = 1;
            readdata_internal = 0;
            read_ram = 1;
        end
        else begin
            waitrequest_cpu = 1;
            readdata_internal = 0;
            read_ram = 0;

        end
    end
    else begin
        write_ram = 0;
        read_ram = 1;
    end

    //Byteenable Implementation
    if(byteenable_cpu[0] == 1)
        hi = readdata_internal[31:24];
    else
        hi = 0;

    if(byteenable_cpu[1] == 1)
        midhi = readdata_internal[23:16];
    else
        midhi = 0;

    if(byteenable_cpu[2] == 1)
        midlo = readdata_internal[15:8];
    else
        midlo = 0;

    if(byteenable_cpu[3] == 1)
        lo = readdata_internal[7:0];
    else
        lo = 0;


    //Ram byteenable
    if(write_cpu) begin
        byteenable_ram = byteenable_cpu;
    end
    else begin
        byteenable_ram = 15;
    end
end


endmodule

rtl_cache/l1cache_tb.v
module l1cache_tb();
logic clk;
logic read_ram;
logic write_ram;
logic[31:0] addr_ram;
logic[3:0] byteenable_ram;
logic [31:0] writedata_ram;
logic [31:0] readdata_ram;
logic waitrequest_ram;

logic read_cpu;
logic write_cpu;
logic[31:0] addr_cpu;
logic[3:0] byteenable_cpu;
logic [31:0] writedata_cpu;
logic [31:0] readdata_cpu;
logic waitrequest_cpu;

logic reset;
logic[31:0] count;

logic[31:0] mem[1023*4];

initial begin
    $dumpfile("waves.vcd");
    $dumpvars(0, l1cache_tb);
end

initial begin
    clk = 0;
    repeat (100)
        #1 clk = ~clk;
    //$finish;
end

initial begin
    reset = 1;
    #2;
    reset=0;
    waitrequest_ram = 0;
    read_cpu =1;
    write_cpu =0;
    byteenable_cpu = 15;

    //Read testing
    //(Write through only, resets block valid flag if found)
    addr_cpu = 16;
    #2;
    while(waitrequest_cpu) begin
        #1;
    end
    #5;

    //From cached block
    addr_cpu = 17;
    #10;

    //From new block to fetch
    addr_cpu = 22;
    #2;
    while(waitrequest_cpu) begin
        #1;
    end
    #5;

    //From cached block
    addr_cpu = 23;
    @(posedge clk);
    #1;

    while(waitrequest_cpu) begin
        #1;
    end
    #10;
    $finish;
end


//Memory emulation
initial begin
    for(int i =0; i<1024*4; i++) begin
        mem[i] = 16*i+1;
    end
end

assign readdata_ram = mem[addr_ram];

l1cache dut(.reset(reset), .clk(clk), .read_cpu(read_cpu), .write_cpu(write_cpu), .addr_cpu(addr_cpu), .byteenable_cpu(byteenable_cpu), .writedata_cpu(writedata_cpu), .readdata_cpu(readdata_cpu), .waitrequest_cpu(waitrequest_cpu), .read_ram(read_ram), .write_ram(write_ram), .addr_ram(addr_ram), .byteenable_ram(byteenable_ram), .writedata_ram(writedata_ram), .readdata_ram(readdata_ram), .waitrequest_ram(waitrequest_ram));
endmodule

rtl_cache/cache.vcd
$date
	Fri Dec 17 20:38:45 2021
$end
$version
	Icarus Verilog
$end
$timescale
	1s
$end
$scope module l1cache_tb $end
$var wire 32 ! readdata_ram [31:0] $end
$var wire 32 " writedata_ram [31:0] $end
$var wire 1 # write_ram $end
$var wire 1 $ waitrequest_cpu $end
$var wire 32 % readdata_cpu [31:0] $end
$var wire 1 & read_ram $end
$var wire 4 ' byteenable_ram [3:0] $end
$var wire 32 ( addr_ram [31:0] $end
$var reg 32 ) addr_cpu [31:0] $end
$var reg 4 * byteenable_cpu [3:0] $end
$var reg 1 + clk $end
$var reg 1 , read_cpu $end
$var reg 1 - reset $end
$var reg 1 . waitrequest_ram $end
$var reg 1 / write_cpu $end
$var reg 32 0 writedata_cpu [31:0] $end
$scope module dut $end
$var wire 32 1 addr_cpu [31:0] $end
$var wire 4 2 byteenable_cpu [3:0] $end
$var wire 1 + clk $end
$var wire 1 , read_cpu $end
$var wire 32 3 readdata_ram [31:0] $end
$var wire 1 - reset $end
$var wire 32 4 viewer_address_queue0 [31:0] $end
$var wire 32 5 viewer_address_queue1 [31:0] $end
$var wire 32 6 viewer_address_queue2 [31:0] $end
$var wire 32 7 viewer_address_queue3 [31:0] $end
$var wire 32 8 viewer_mem0 [31:0] $end
$var wire 32 9 viewer_mem1 [31:0] $end
$var wire 32 : viewer_mem2 [31:0] $end
$var wire 32 ; viewer_mem3 [31:0] $end
$var wire 20 < viewer_tag [19:0] $end
$var wire 1 = viewer_valid $end
$var wire 1 . waitrequest_ram $end
$var wire 1 / write_cpu $end
$var wire 32 > writedata_cpu [31:0] $end
$var reg 32 ? addr_ram [31:0] $end
$var reg 10 @ block_id_cpu [9:0] $end
$var reg 4 A byteenable_ram [3:0] $end
$var reg 8 B hi [7:0] $end
$var reg 1 C hit $end
$var reg 10 D last_block_id_ram [9:0] $end
$var reg 32 E last_queue_address [31:0] $end
$var reg 1 F last_queue_valid $end
$var reg 1 G last_ram_read $end
$var reg 1 H last_ram_waitrequest $end
$var reg 1 I last_ram_write $end
$var reg 20 J last_tag_ram [19:0] $end
$var reg 8 K lo [7:0] $end
$var reg 8 L midhi [7:0] $end
$var reg 8 M midlo [7:0] $end
$var reg 1 & read_ram $end
$var reg 32 N readdata_cpu [31:0] $end
$var reg 32 O readdata_internal [31:0] $end
$var reg 20 P tag_cpu [19:0] $end
$var reg 4 Q valid_queue [3:0] $end
$var reg 1 $ waitrequest_cpu $end
$var reg 1 # write_ram $end
$var reg 32 R writedata_ram [31:0] $end
$scope begin $ivl_for_loop1 $end
$var integer 32 S i [31:0] $end
$upscope $end
$upscope $end
$scope begin $ivl_for_loop0 $end
$var integer 32 T i [31:0] $end
$upscope $end
$upscope $end
$enddefinitions $end
#0
$dumpvars
b1000000000000 T
b0 S
bx R
bx Q
bx P
bx O
bx N
bx M
bx L
bx K
bx J
xI
xH
xG
xF
bx E
bx D
xC
bx B
bx A
bx @
bx ?
bx >
x=
bx <
bx ;
bx :
bx 9
bx 8
bx 7
bx 6
bx 5
bx 4
bx 3
bx 2
bx 1
bx 0
x/
x.
1-
x,
0+
bx *
bx )
bx (
bx '
x&
bx %
x$
x#
bx "
bx !
$end
#1
b1111 '
b1111 A
b0 K
b0 M
b0 L
b0 B
1&
0#
b0x J
b0 <
0=
0F
b0 Q
b10000000000 S
1+
#2
0&
b0 O
1$
0C
b100 @
b0 P
0+
b10000 )
b10000 1
b1111 *
b1111 2
0/
1,
0.
0-
#3
1&
b100110001 !
b100110001 3
b10011 (
b10011 ?
b10011 4
b10010 5
b10001 6
b10000 7
b1111 Q
0G
0I
0H
b0 %
b0 N
1+
#4
0+
#5
b100100001 !
b100100001 3
b10010 (
b10010 ?
b100 D
b0 J
b10010 4
b10001 5
b10000 6
b0 7
b111 Q
1G
1F
b10011 E
1+
#6
0+
#7
b100010001 !
b100010001 3
b10001 (
b10001 ?
b10001 4
b10000 5
b0 6
b11 Q
b100100001 ;
b10010 E
1+
#8
0+
#9
b100000001 !
b100000001 3
b10000 (
b10000 ?
b10000 4
b0 5
b1 Q
b100010001 :
b10001 E
1+
#10
0+
#11
0&
b1 !
b1 3
b0 (
b0 ?
b0 4
b0 Q
b100000001 9
b10000 E
1+
#12
0+
#13
b1 K
b1 O
0$
b0 D
1C
1=
b1 8
0G
0F
b0 E
1+
#14
0+
#15
b1 %
b1 N
1+
#16
0+
#17
1+
#18
0+
#19
b100000001 %
b100000001 N
b1 M
b100000001 O
1+
b10001 )
b10001 1
#20
0+
#21
1+
#22
0+
#23
1+
#24
0+
#25
1+
#26
0+
#27
1+
#28
0+
#29
1&
b101110001 !
b101110001 3
b10111 (
b10111 ?
b10111 4
b10110 5
b10101 6
b10100 7
b1111 Q
b0 %
b0 N
b0 K
b0 M
b0 O
1$
0C
b101 @
1+
b10110 )
b10110 1
#30
0+
#31
b101100001 !
b101100001 3
b10110 (
b10110 ?
b101 D
b1 J
b10110 4
b10101 5
b10100 6
b0 7
b111 Q
1G
1F
b10111 E
1+
#32
0+
#33
b101010001 !
b101010001 3
b10101 (
b10101 ?
b10101 4
b10100 5
b0 6
b11 Q
b10110 E
1+
#34
0+
#35
b101000001 !
b101000001 3
b10100 (
b10100 ?
b10100 4
b0 5
b1 Q
b10101 E
1+
#36
0+
#37
0&
b1 !
b1 3
b0 (
b0 ?
b0 4
b0 Q
b10100 E
1+
#38
0+
#39
b1010001 K
b1 M
b101010001 O
0$
b0 D
b0 J
1C
0G
0F
b0 E
1+
#40
0+
#41
b101010001 %
b101010001 N
1+
#42
0+
#43
1+
#44
0+
#45
b101100001 %
b101100001 N
b1100001 K
b101100001 O
1+
b10111 )
b10111 1
